coral/__init__.py
coral/py.typed
coral/cli/__init__.py
coral/cli/main.py
coral/compression/__init__.py
coral/compression/pruning.py
coral/compression/quantization.py
coral/core/__init__.py
coral/core/deduplicator.py
coral/core/weight_tensor.py
coral/delta/__init__.py
coral/delta/compression.py
coral/delta/delta_encoder.py
coral/integrations/__init__.py
coral/integrations/pytorch.py
coral/storage/__init__.py
coral/storage/hdf5_store.py
coral/storage/weight_store.py
coral/training/__init__.py
coral/training/checkpoint_manager.py
coral/training/training_state.py
coral/utils/__init__.py
coral/utils/visualization.py
coral/version_control/__init__.py
coral/version_control/branch.py
coral/version_control/commit.py
coral/version_control/repository.py
coral/version_control/version.py
coral_ml-1.0.0.dist-info/licenses/LICENSE
coral_ml-1.0.0.dist-info/METADATA
coral_ml-1.0.0.dist-info/WHEEL
coral_ml-1.0.0.dist-info/entry_points.txt
coral_ml-1.0.0.dist-info/top_level.txt
coral_ml-1.0.0.dist-info/RECORD
