Metadata-Version: 2.4
Name: coral-ml
Version: 1.0.0
Summary: Neural network weight storage and deduplication system
Home-page: https://github.com/parkerdgabel/coral
Author: Coral Contributors
License: MIT
Project-URL: Homepage, https://github.com/parkerdgabel/coral
Project-URL: Bug Tracker, https://github.com/parkerdgabel/coral/issues
Project-URL: Source, https://github.com/parkerdgabel/coral
Project-URL: Documentation, https://github.com/parkerdgabel/coral#readme
Keywords: machine-learning,neural-networks,weight-management,model-versioning,deduplication,delta-encoding,ml-ops,model-storage,version-control
Classifier: Development Status :: 5 - Production/Stable
Classifier: Intended Audience :: Developers
Classifier: License :: OSI Approved :: MIT License
Classifier: Programming Language :: Python :: 3
Classifier: Programming Language :: Python :: 3.8
Classifier: Programming Language :: Python :: 3.9
Classifier: Programming Language :: Python :: 3.10
Classifier: Programming Language :: Python :: 3.11
Classifier: Topic :: Scientific/Engineering :: Artificial Intelligence
Requires-Python: >=3.8
License-File: LICENSE
Requires-Dist: numpy>=1.21.0
Requires-Dist: h5py>=3.0.0
Requires-Dist: protobuf>=3.19.0
Requires-Dist: xxhash>=3.0.0
Requires-Dist: tqdm>=4.60.0
Requires-Dist: networkx>=3.1
Requires-Dist: click>=8.1.8
Provides-Extra: dev
Requires-Dist: pytest>=7.0.0; extra == "dev"
Requires-Dist: pytest-cov>=3.0.0; extra == "dev"
Requires-Dist: ruff>=0.1.0; extra == "dev"
Requires-Dist: mypy>=0.950; extra == "dev"
Provides-Extra: torch
Requires-Dist: torch>=1.10.0; extra == "torch"
Provides-Extra: tensorflow
Requires-Dist: tensorflow>=2.8.0; extra == "tensorflow"
Dynamic: home-page
Dynamic: license-file
Dynamic: requires-python
